Profe/rom/rom.v
module rom_custom(
  input [3:0] addr,
  output reg [7:0] data_out
);

  reg [7:0] mem [0:15];

  initial begin
    mem[0] = 8'hAA;
    mem[1] = 8'hBB;
    mem[2] = 8'hCC;
    mem[3] = 8'hDD;
    mem[4] = 8'hEE;
    mem[5] = 8'hFF;
    mem[6] = 8'h11;
    mem[7] = 8'h22;
    mem[8] = 8'h33;
    mem[9] = 8'h44;
    mem[10] = 8'h55;
    mem[11] = 8'h66;
    mem[12] = 8'h77;
    mem[13] = 8'h88;
    mem[14] = 8'h99;
    mem[15] = 8'h00;
  end

  always @(*) begin
    data_out = mem[addr];
  end

endmodule

Profe/rom/rom_tb.v
`timescale 1ns / 1ps
`include "rom.v"
module tb_rom_custom;
  reg [3:0] addr;
  wire [7:0] data_out;

  rom_custom rom_inst(addr, data_out);

  initial begin
    $dumpfile("rom_custom.vcd");
    $dumpvars(0, tb_rom_custom);

    addr = 0; #10;
    addr = 1; #10;
    addr = 2; #10;
    addr = 3; #10;
    addr = 4; #10;
    addr = 5; #10;
    addr = 6; #10;
    addr = 7; #10;

    $finish;
  end

endmodule

Profe/rom/rom_custom.vcd
$date
	Sun Aug 10 23:50:44 2025
$end
$version
	Icarus Verilog
$end
$timescale
	1ps
$end
$scope module tb_rom_custom $end
$var wire 8 ! data_out [7:0] $end
$var reg 4 " addr [3:0] $end
$scope module rom_inst $end
$var wire 4 # addr [3:0] $end
$var reg 8 $ data_out [7:0] $end
$upscope $end
$upscope $end
$enddefinitions $end
#0
$dumpvars
b10101010 $
b0 #
b0 "
b10101010 !
$end
#10000
b10111011 !
b10111011 $
b1 "
b1 #
#20000
b11001100 !
b11001100 $
b10 "
b10 #
#30000
b11011101 !
b11011101 $
b11 "
b11 #
#40000
b11101110 !
b11101110 $
b100 "
b100 #
#50000
b11111111 !
b11111111 $
b101 "
b101 #
#60000
b10001 !
b10001 $
b110 "
b110 #
#70000
b100010 !
b100010 $
b111 "
b111 #
