Ejercicios/Ej1/full_adder.v
/*Diseñe un módulo en Verilog que implemente un sumador completo de un bit con entradas a,b y
cin(carry in), y salidas sum y cout (carry out). Describir y simular con Icarus Verilog + GTKWave.*/

module full_adder(
  input a,
  input b,
  input cin,
  output sum,
  output carry
);

assign sum = a ^ b ^ cin;                         // suma: XOR de a, b y cin
assign carry = (a & b) | (b & cin) | (cin & a);  // carry: combinación de AND y OR

endmodule

Ejercicios/Ej1/full_adder_tb.v
`timescale 1ns / 1ps
`include "full_adder.v"

// Testbench
module full_adder_tb;

// declaracion de las señales de entrada y de salida
  reg a, b, cin;
  wire sum, carry;

// Instanciación del módulo full_adder
  full_adder uut (
    .a(a),
    .b(b),
    .cin(cin),
    .sum(sum),
    .carry(carry)
  );

// Generación de combinaciones para las entradas
  initial begin
    $dumpfile("full_adder.vcd");
    $dumpvars(0,full_adder_tb);

    $monitor("At time %0t: a=%b, b=%b, cin=%b -> sum=%b, carry=%b", $time, a, b, cin, sum, carry);

    // Probar todas las combinaciones posibles de entradas
    a = 0; b = 0; cin = 0; #10;
    a = 0; b = 0; cin = 1; #10;
    a = 0; b = 1; cin = 0; #10;
    a = 0; b = 1; cin = 1; #10;
    a = 1; b = 0; cin = 0; #10;
    a = 1; b = 0; cin = 1; #10;
    a = 1; b = 1; cin = 0; #10;
    a = 1; b = 1; cin = 1; #10;

    $finish;  // Finaliza la simulación
  end
endmodule

Profe/full_adder/full_adder.vcd
$date
	Sun Aug 10 00:25:22 2025
$end
$version
	Icarus Verilog
$end
$timescale
	1ps
$end
$scope module full_adder_tb $end
$var wire 1 ! sum $end
$var wire 1 " carry $end
$var reg 1 # a $end
$var reg 1 $ b $end
$var reg 1 % cin $end
$scope module uut $end
$var wire 1 # a $end
$var wire 1 $ b $end
$var wire 1 " carry $end
$var wire 1 % cin $end
$var wire 1 ! sum $end
$upscope $end
$upscope $end
$enddefinitions $end
#0
$dumpvars
0%
0$
0#
0"
0!
$end
#10000
1!
1%
#20000
0%
1$
#30000
1"
0!
1%
#40000
0"
1!
0%
0$
1#
#50000
1"
0!
1%
#60000
0%
1$
#70000
1!
1%
